crateman/__init__.py
crateman/cli.py
crateman/config.py
crateman/crate.py
crateman/exception.py
crateman/log.py
crateman/resolver.py
crateman-1.0.2.dist-info/METADATA
crateman-1.0.2.dist-info/WHEEL
crateman-1.0.2.dist-info/entry_points.txt
crateman-1.0.2.dist-info/top_level.txt
crateman-1.0.2.dist-info/RECORD
