Metadata-Version: 2.1
Name: crateman
Version: 1.0.2
Summary: Build system focused on resolving and building dependencies.
Author-email: lch361 <surperior64@gmail.com>
License: GPL-3.0
Project-URL: Homepage, https://gitlab.com/lch361/crateman
Keywords: build,system,dependency,package,manager,development
Classifier: Topic :: Software Development :: Build Tools
Classifier: Topic :: Utilities
Classifier: Operating System :: POSIX :: Linux
Classifier: Programming Language :: Python :: 3
Classifier: Intended Audience :: Developers
Requires-Dist: toml
